screen_games/__init__.py
screen_games/config.py
screen_games/envs/__init__.py
screen_games/envs/dino.py
screen_games/envs/dino_slow.py
screen_games/envs/screen.py
screen_games-0.0.3.dist-info/METADATA
screen_games-0.0.3.dist-info/WHEEL
screen_games-0.0.3.dist-info/licenses/LICENSE
screen_games-0.0.3.dist-info/RECORD
